bincopy.py
bincopy-20.0.0.dist-info/LICENSE
bincopy-20.0.0.dist-info/METADATA
bincopy-20.0.0.dist-info/WHEEL
bincopy-20.0.0.dist-info/entry_points.txt
bincopy-20.0.0.dist-info/top_level.txt
bincopy-20.0.0.dist-info/RECORD
