Metadata-Version: 2.1
Name: bincopy
Version: 20.0.0
Summary: Mangling of various file formats that conveys binary information (Motorola S-Record, Intel HEX and binary files).
Home-page: https://github.com/eerimoq/bincopy
Author: Erik Moqvist
Author-email: erik.moqvist@gmail.com
License: MIT
Keywords: srecord,srec,intel hex,binary,.s19,.s28,.s37,.hex
Classifier: License :: OSI Approved :: MIT License
Classifier: Programming Language :: Python :: 3.6
Classifier: Programming Language :: Python :: 3.7
Classifier: Programming Language :: Python :: 3.8
Classifier: Programming Language :: Python :: 3.9
Requires-Python: >=3.6
License-File: LICENSE
Requires-Dist: humanfriendly
Requires-Dist: argparse_addons>=0.4.0
Requires-Dist: pyelftools
